depthlib/MonocularDepthEstimator.py
depthlib/StereoDepthEstimator.py
depthlib/StereoDepthEstimatorVideo.py
depthlib/__init__.py
depthlib/input.py
depthlib/postprocess.py
depthlib/rectify.py
depthlib/stereo_core.py
depthlib/threaded_stereo.py
depthlib/visualizations.py
depthlib-0.1.1.dist-info/licenses/LICENSE
depthlib-0.1.1.dist-info/METADATA
depthlib-0.1.1.dist-info/WHEEL
depthlib-0.1.1.dist-info/top_level.txt
depthlib-0.1.1.dist-info/RECORD
