Metadata-Version: 2.4
Name: depthlib
Version: 0.1.1
Summary: A library for depth estimation and processing
Author: Piyush Gupta, Himangshu Dikshit, Vedic Yadav
License-Expression: MIT
Project-URL: Repository, https://github.com/fampiyush/DepthEstimation
Requires-Python: >=3.9
License-File: LICENSE
Requires-Dist: numpy>=2.2.6
Requires-Dist: opencv-python>=4.12.0.88
Requires-Dist: pillow>=11.3.0
Requires-Dist: python-dateutil>=2.9.0.post0
Requires-Dist: matplotlib>=3.10.6
Requires-Dist: transformers>=4.57.1
Dynamic: license-file
